rust_q-0.1.0.dist-info/METADATA
rust_q-0.1.0.dist-info/WHEEL
rust_q/__init__.py
rust_q/rust_q.abi3.so
rust_q-0.1.0.dist-info/RECORD
