Metadata-Version: 2.3
Name: rust-q
Version: 0.1.0
